{
	"configurations" : 
	[
		{
			"directories" : 
			[
				{
					"build" : ".",
					"hasInstallRule" : true,
					"jsonFile" : "directory-.-52f8752ccd4bba5abe96.json",
					"minimumCMakeVersion" : 
					{
						"string" : "3.12"
					},
					"projectIndex" : 0,
					"source" : ".",
					"targetIndexes" : 
					[
						0,
						1,
						2
					]
				}
			],
			"name" : "",
			"projects" : 
			[
				{
					"directoryIndexes" : 
					[
						0
					],
					"name" : "robot_pose_publisher_ros2",
					"targetIndexes" : 
					[
						0,
						1,
						2
					]
				}
			],
			"targets" : 
			[
				{
					"directoryIndex" : 0,
					"id" : "robot_pose_publisher::@6890427a1f51a3e7e1df",
					"jsonFile" : "target-robot_pose_publisher-fd961cc124332d03199a.json",
					"name" : "robot_pose_publisher",
					"projectIndex" : 0
				},
				{
					"directoryIndex" : 0,
					"id" : "robot_pose_publisher_ros2_uninstall::@6890427a1f51a3e7e1df",
					"jsonFile" : "target-robot_pose_publisher_ros2_uninstall-d800075405e57249b3f4.json",
					"name" : "robot_pose_publisher_ros2_uninstall",
					"projectIndex" : 0
				},
				{
					"directoryIndex" : 0,
					"id" : "uninstall::@6890427a1f51a3e7e1df",
					"jsonFile" : "target-uninstall-fac57b0442a64e3ec720.json",
					"name" : "uninstall",
					"projectIndex" : 0
				}
			]
		}
	],
	"kind" : "codemodel",
	"paths" : 
	{
		"build" : "/home/natdanai/ROS_Source_Code/yahboomcar_ws/function_package_without_WiFi_module/yahboomcar_ws/build/robot_pose_publisher_ros2",
		"source" : "/home/natdanai/ROS_Source_Code/yahboomcar_ws/function_package_without_WiFi_module/yahboomcar_ws/src/robot_pose_publisher_ros2"
	},
	"version" : 
	{
		"major" : 2,
		"minor" : 3
	}
}
